lcd/__init__.py
lcd/i2c_pcf8574_interface.py
lcd/lcd.py
lcd/pin_mapping.py
I2C_HD77480_LCD-0.1.1.dist-info/LICENSE
I2C_HD77480_LCD-0.1.1.dist-info/METADATA
I2C_HD77480_LCD-0.1.1.dist-info/WHEEL
I2C_HD77480_LCD-0.1.1.dist-info/top_level.txt
I2C_HD77480_LCD-0.1.1.dist-info/RECORD
