Metadata-Version: 2.1
Name: I2C-HD77480-LCD
Version: 0.1.1
Summary: LCD driver for HD4480 behind PCF8574
Home-page: https://github.com/maystar/I2C_HD77480_LCD
Author: Fabian
License: MIT
Platform: UNKNOWN
Requires-Python: >=3.7
License-File: LICENSE
